{
  "user_id": "user_0048",
  "timestamp": "2025-11-10T09:04:14.806828",
  "phase": "behavioral_signals",
  "signals": {
    "subscriptions": {
      "30d": {
        "recurring_count": 0,
        "monthly_recurring_spend": 0.0,
        "subscription_share_pct": 0.0,
        "recurring_merchants": []
      },
      "180d": {
        "recurring_count": 0,
        "monthly_recurring_spend": 0.0,
        "subscription_share_pct": 0.0,
        "recurring_merchants": []
      }
    },
    "savings": {
      "30d": {
        "net_inflow": 0.0,
        "growth_rate_pct": 0.0,
        "emergency_fund_months": 8.17,
        "savings_balance": 43807.95
      },
      "180d": {
        "net_inflow": 0.0,
        "growth_rate_pct": 0.0,
        "emergency_fund_months": 6.06,
        "savings_balance": 43807.95
      }
    },
    "credit": {
      "current": {
        "max_utilization_pct": 0.0,
        "avg_utilization_pct": 0.0,
        "flag_30": false,
        "flag_50": false,
        "flag_80": false,
        "min_payment_only": false,
        "has_interest": false,
        "is_overdue": false,
        "num_credit_cards": 0,
        "utilization_by_card": [],
        "interest_charges_present": false,
        "interest_charges_amount_60d": 0.0
      }
    },
    "income": {
      "30d": {
        "median_pay_gap_days": 0,
        "income_variability": 0.0,
        "cash_buffer_months": 0.0,
        "pay_frequency": "unknown",
        "num_paychecks": 1,
        "avg_paycheck": 0.0
      },
      "180d": {
        "median_pay_gap_days": 14,
        "income_variability": 0.3385,
        "cash_buffer_months": 0.38,
        "pay_frequency": "biweekly",
        "num_paychecks": 12,
        "avg_paycheck": 3814.74
      }
    }
  },
  "persona_assignment": {
    "persona": "Cash Flow Optimizer",
    "criteria_met": {
      "cash_buffer_months": 0.38,
      "low_growth_rate_pct": 0.0,
      "low_net_inflow": 0.0,
      "stable_income_pay_gap_days": 14
    },
    "all_checks": {
      "High Utilization": {},
      "Variable Income Budgeter": {
        "cash_buffer_months": 0.38
      },
      "Subscription-Heavy": {},
      "Cash Flow Optimizer": {
        "cash_buffer_months": 0.38,
        "low_growth_rate_pct": 0.0,
        "low_net_inflow": 0.0,
        "stable_income_pay_gap_days": 14
      },
      "Savings Builder": {
        "low_utilization": 0.0
      }
    },
    "timestamp": "2025-11-10T09:04:16.853380"
  }
}